jsii/__init__.py
jsii/__meta__.py
jsii/_compat.py
jsii/_metadata.json
jsii/_reference_map.py
jsii/_runtime.py
jsii/_utils.py
jsii/compat.py
jsii/errors.py
jsii/py.typed
jsii/python.py
jsii/_embedded/__init__.py
jsii/_embedded/jsii/__init__.py
jsii/_embedded/jsii/bin__jsii-runtime.js
jsii/_embedded/jsii/bin__jsii-runtime.js.map
jsii/_embedded/jsii/lib__program.js
jsii/_embedded/jsii/lib__program.js.map
jsii/_kernel/__init__.py
jsii/_kernel/types.py
jsii/_kernel/providers/__init__.py
jsii/_kernel/providers/base.py
jsii/_kernel/providers/process.py
jsii-1.123.0.dist-info/licenses/LICENSE
jsii-1.123.0.dist-info/licenses/NOTICE
jsii-1.123.0.dist-info/METADATA
jsii-1.123.0.dist-info/WHEEL
jsii-1.123.0.dist-info/top_level.txt
jsii-1.123.0.dist-info/RECORD
