Metadata-Version: 2.4
Name: jsii
Version: 1.123.0
Summary: Python client for jsii runtime
Home-page: https://github.com/aws/jsii
Author: Amazon Web Services
License: Apache-2.0
Project-URL: Bug Tracker, https://github.com/aws/jsii
Project-URL: Source, https://github.com/aws/jsii.git
Classifier: Development Status :: 5 - Production/Stable
Classifier: Intended Audience :: Developers
Classifier: License :: OSI Approved :: Apache Software License
Classifier: Programming Language :: JavaScript
Classifier: Programming Language :: Python :: 3 :: Only
Classifier: Programming Language :: Python :: 3.9
Classifier: Programming Language :: Python :: 3.10
Classifier: Programming Language :: Python :: 3.11
Classifier: Topic :: Software Development :: Libraries
Classifier: Topic :: Utilities
Classifier: Typing :: Typed
Requires-Python: ~=3.9
License-File: LICENSE
License-File: NOTICE
Requires-Dist: attrs<26.0,>=21.2
Requires-Dist: cattrs<25.4,>=1.8
Requires-Dist: importlib_resources>=5.2.0
Requires-Dist: publication>=0.0.3
Requires-Dist: typeguard==2.13.3
Requires-Dist: python-dateutil
Requires-Dist: typing_extensions<5.0,>=3.8
Dynamic: author
Dynamic: classifier
Dynamic: description
Dynamic: description-content-type
Dynamic: home-page
Dynamic: license
Dynamic: license-file
Dynamic: project-url
Dynamic: requires-dist
Dynamic: requires-python
Dynamic: summary
